README.rst
setup.py
ip2geo/__init__.py
ip2geo/ip2geo.py
ip2geo.egg-info/PKG-INFO
ip2geo.egg-info/SOURCES.txt
ip2geo.egg-info/dependency_links.txt
ip2geo.egg-info/entry_points.txt
ip2geo.egg-info/top_level.txt