Metadata-Version: 1.0
Name: ip2geo
Version: 0.2
Summary: Get geolocation from IP address or hostname
Home-page: https://github.com/pdrb/ip2geo
Author: Pedro Buteri Gonring
Author-email: pedro@bigode.net
License: MIT
Keywords: ip geo geolocation ip-api.com freegeoip.net ipinfo.io
Platform: UNKNOWN
